hackrf/__init__.py
hackrf/keyfob_detector.grc
hackrf/rf_detector.py
integration/__init__.py
integration/integrated_detector.py
logs/dashboard/.gitkeep
logs/integrated/.gitkeep
openxc/__init__.py
openxc/rf_simulator.py
rf_signal_monitor/dashboard.py
rf_signal_monitor/main_application.py
rf_signal_monitor-0.3.0.dist-info/licenses/LICENSE
rf_signal_monitor-0.3.0.dist-info/METADATA
rf_signal_monitor-0.3.0.dist-info/WHEEL
rf_signal_monitor-0.3.0.dist-info/entry_points.txt
rf_signal_monitor-0.3.0.dist-info/top_level.txt
rf_signal_monitor-0.3.0.dist-info/RECORD
