Metadata-Version: 2.4
Name: rf_signal_monitor
Version: 0.3.0
Summary: RF Signal Monitor for automotive security and vehicle signal analysis
Author-email: Jonathan Marien <jondmarien@gmail.com>
License: MIT License
Project-URL: Homepage, https://github.com/jondmarien/automotive-security-poc
Project-URL: Bug Tracker, https://github.com/jondmarien/automotive-security-poc/issues
Keywords: automotive,security,RF,vehicle,OpenXC,HackRF
Classifier: Development Status :: 3 - Alpha
Classifier: Intended Audience :: Developers
Classifier: License :: OSI Approved :: MIT License
Classifier: Programming Language :: Python :: 3
Classifier: Programming Language :: Python :: 3.9
Classifier: Topic :: Security
Classifier: Topic :: Scientific/Engineering :: Information Analysis
Requires-Python: >=3.9
License-File: LICENSE
Requires-Dist: pyserial>=3.5
Requires-Dist: rich>=12.0.0
Requires-Dist: matplotlib>=3.5.0
Requires-Dist: numpy>=1.22.0
Requires-Dist: pandas>=1.4.0
Requires-Dist: PyQt5>=5.15.0
Requires-Dist: requests>=2.27.0
Provides-Extra: sdr
Requires-Dist: gnuradio>=3.8.0; extra == "sdr"
Dynamic: license-file
